public class Hello {
    public static void main(String[] args) {
        int i = 1;
        int j = 2;
        double a = i / j;
        double b = i * j;
        double c = i + j;
        double d = i - j;
        if (i == 1) {
            for (int x = 0; x < j; x++) {
                System.out.println(i + " " + x);
            }
        }
    }
}

javap -c Hello.class
 Compiled from "Hello.java"
public class com.boluomi.week01.Hello {
  public com.boluomi.week01.Hello();
    Code:
       0: aload_0
       1: invokespecial #1                  // Method java/lang/Object."<init>":()V
       4: return

  public static void main(java.lang.String[]);
    Code:
       0: iconst_1
       1: istore_1
       2: iconst_2
       3: istore_2
       4: iload_1
       5: iload_2
       6: idiv
       7: i2d
       8: dstore_3
       9: iload_1
      10: iload_2
      11: imul
      12: i2d
      13: dstore        5
      15: iload_1
      16: iload_2
      17: iadd
      18: i2d
      19: dstore        7
      21: iload_1
      22: iload_2
      23: isub
      24: i2d
      25: dstore        9
      27: iload_1
      28: iconst_1
      29: if_icmpne     77
      32: iconst_0
      33: istore        11
      35: iload         11
      37: iload_2
      38: if_icmpge     77
      41: getstatic     #2                  // Field java/lang/System.out:Ljava/io/PrintStream;
      44: new           #3                  // class java/lang/StringBuilder
      47: dup
      48: invokespecial #4                  // Method java/lang/StringBuilder."<init>":()V
      51: iload_1
      52: invokevirtual #5                  // Method java/lang/StringBuilder.append:(I)Ljava/lang/StringBuilder;
      55: ldc           #6                  // String
      57: invokevirtual #7                  // Method java/lang/StringBuilder.append:(Ljava/lang/String;)Ljava/lang/StringBuilder;
      60: iload         11
      62: invokevirtual #5                  // Method java/lang/StringBuilder.append:(I)Ljava/lang/StringBuilder;
      65: invokevirtual #8                  // Method java/lang/StringBuilder.toString:()Ljava/lang/String;
      68: invokevirtual #9                  // Method java/io/PrintStream.println:(Ljava/lang/String;)V
      71: iinc          11, 1
      74: goto          35
      77: return
}

复杂 javap -c -verbose Hello.class
Classfile /E:/study-source/boluomi/src/main/java/com/boluomi/week01/Hello.class
  Last modified 2021-1-10; size 784 bytes
  MD5 checksum 792d92fc826a50b325c48a89b7bc2d6c
  Compiled from "Hello.java"
public class com.boluomi.week01.Hello
  minor version: 0
  major version: 52
  flags: ACC_PUBLIC, ACC_SUPER
Constant pool:
   #1 = Methodref          #11.#22        // java/lang/Object."<init>":()V
   #2 = Fieldref           #23.#24        // java/lang/System.out:Ljava/io/PrintStream;
   #3 = Class              #25            // java/lang/StringBuilder
   #4 = Methodref          #3.#22         // java/lang/StringBuilder."<init>":()V
   #5 = Methodref          #3.#26         // java/lang/StringBuilder.append:(I)Ljava/lang/StringBuilder;
   #6 = String             #27            //
   #7 = Methodref          #3.#28         // java/lang/StringBuilder.append:(Ljava/lang/String;)Ljava/lang/StringBuilder;
   #8 = Methodref          #3.#29         // java/lang/StringBuilder.toString:()Ljava/lang/String;
   #9 = Methodref          #30.#31        // java/io/PrintStream.println:(Ljava/lang/String;)V
  #10 = Class              #32            // com/boluomi/week01/Hello
  #11 = Class              #33            // java/lang/Object
  #12 = Utf8               <init>
  #13 = Utf8               ()V
  #14 = Utf8               Code
  #15 = Utf8               LineNumberTable
  #16 = Utf8               main
  #17 = Utf8               ([Ljava/lang/String;)V
  #18 = Utf8               StackMapTable
  #19 = Class              #34            // "[Ljava/lang/String;"
  #20 = Utf8               SourceFile
  #21 = Utf8               Hello.java
  #22 = NameAndType        #12:#13        // "<init>":()V
  #23 = Class              #35            // java/lang/System
  #24 = NameAndType        #36:#37        // out:Ljava/io/PrintStream;
  #25 = Utf8               java/lang/StringBuilder
  #26 = NameAndType        #38:#39        // append:(I)Ljava/lang/StringBuilder;
  #27 = Utf8
  #28 = NameAndType        #38:#40        // append:(Ljava/lang/String;)Ljava/lang/StringBuilder;
  #29 = NameAndType        #41:#42        // toString:()Ljava/lang/String;
  #30 = Class              #43            // java/io/PrintStream
  #31 = NameAndType        #44:#45        // println:(Ljava/lang/String;)V
  #32 = Utf8               com/boluomi/week01/Hello
  #33 = Utf8               java/lang/Object
  #34 = Utf8               [Ljava/lang/String;
  #35 = Utf8               java/lang/System
  #36 = Utf8               out
  #37 = Utf8               Ljava/io/PrintStream;
  #38 = Utf8               append
  #39 = Utf8               (I)Ljava/lang/StringBuilder;
  #40 = Utf8               (Ljava/lang/String;)Ljava/lang/StringBuilder;
  #41 = Utf8               toString
  #42 = Utf8               ()Ljava/lang/String;
  #43 = Utf8               java/io/PrintStream
  #44 = Utf8               println
  #45 = Utf8               (Ljava/lang/String;)V
{
  public com.boluomi.week01.Hello();
    descriptor: ()V
    flags: ACC_PUBLIC
    Code:
      stack=1, locals=1, args_size=1
         0: aload_0
         1: invokespecial #1                  // Method java/lang/Object."<init>":()V
         4: return
      LineNumberTable:
        line 8: 0

  public static void main(java.lang.String[]);
    descriptor: ([Ljava/lang/String;)V
    flags: ACC_PUBLIC, ACC_STATIC
    Code:
      stack=3, locals=12, args_size=1
         0: iconst_1     将int型(1)推送至栈顶
         1: istore_1     将栈顶int型数值存入第二个本地变量
         2: iconst_2
         3: istore_2
         4: iload_1
         5: iload_2
         6: idiv
         7: i2d
         8: dstore_3
         9: iload_1
        10: iload_2
        11: imul
        12: i2d
        13: dstore        5
        15: iload_1
        16: iload_2
        17: iadd
        18: i2d
        19: dstore        7
        21: iload_1
        22: iload_2
        23: isub
        24: i2d
        25: dstore        9
        27: iload_1
        28: iconst_1
        29: if_icmpne     77
        32: iconst_0
        33: istore        11
        35: iload         11
        37: iload_2
        38: if_icmpge     77
        41: getstatic     #2                  // Field java/lang/System.out:Ljava/io/PrintStream;
        44: new           #3                  // class java/lang/StringBuilder
        47: dup
        48: invokespecial #4                  // Method java/lang/StringBuilder."<init>":()V
        51: iload_1
        52: invokevirtual #5                  // Method java/lang/StringBuilder.append:(I)Ljava/lang/StringBuilder;
        55: ldc           #6                  // String
        57: invokevirtual #7                  // Method java/lang/StringBuilder.append:(Ljava/lang/String;)Ljava/lang/StringBuilder;
        60: iload         11
        62: invokevirtual #5                  // Method java/lang/StringBuilder.append:(I)Ljava/lang/StringBuilder;
        65: invokevirtual #8                  // Method java/lang/StringBuilder.toString:()Ljava/lang/String;
        68: invokevirtual #9                  // Method java/io/PrintStream.println:(Ljava/lang/String;)V
        71: iinc          11, 1
        74: goto          35
        77: return
      LineNumberTable:
        line 10: 0
        line 11: 2
        line 12: 4
        line 13: 9
        line 14: 15
        line 15: 21
        line 16: 27
        line 17: 32
        line 18: 41
        line 17: 71
        line 21: 77
      StackMapTable: number_of_entries = 2
        frame_type = 255 /* full_frame */
          offset_delta = 35
          locals = [ class "[Ljava/lang/String;", int, int, double, double, double, double, int ]
          stack = []
        frame_type = 250 /* chop */
          offset_delta = 41
}
SourceFile: "Hello.java"
